lstmAttention_utils/__init__.py
lstmAttention_utils/base_Conf.py
lstmAttention_utils/data_loader.py
lstmAttention_utils/process.py
tests/__init__.py
tests/test_datautils.py
lstmAttention_utils-1.0.2.dist-info/LICENSE
lstmAttention_utils-1.0.2.dist-info/METADATA
lstmAttention_utils-1.0.2.dist-info/WHEEL
lstmAttention_utils-1.0.2.dist-info/top_level.txt
lstmAttention_utils-1.0.2.dist-info/RECORD
