Metadata-Version: 2.1
Name: lstmAttention_utils
Version: 1.0.2
Summary: A utility package for processing data for LSTM Attention models in relation classification
Author: Mango.AX
Classifier: Programming Language :: Python :: 3
Classifier: License :: OSI Approved :: MIT License
Classifier: Operating System :: OS Independent
Requires-Python: >=3.7
License-File: LICENSE
Requires-Dist: torch>=1.7.0
Requires-Dist: shutup>=0.2.0
